{
    "steps": [
        {
            "current": {
                "tokens": [
                    "(define",
                    "-f",
                    "un",
                    " inv",
                    " ((",
                    "s",
                    " (",
                    "Bit",
                    "Vec",
                    " ",
                    "4",
                    "))",
                    " (",
                    "t",
                    " (",
                    "Bit",
                    "Vec",
                    " ",
                    "4",
                    ")))",
                    " (",
                    "Bit",
                    "Vec",
                    " ",
                    "4",
                    ")",
                    " (",
                    "bv",
                    "and",
                    " (",
                    "bv",
                    "not",
                    " t",
                    ")",
                    " #",
                    "x",
                    "8",
                    "))",
                    "<|eot_id|>"
                ],
                "token_ids": [
                    69647,
                    2269,
                    359,
                    1558,
                    1819,
                    82,
                    320,
                    8509,
                    10256,
                    220,
                    19,
                    595,
                    320,
                    83,
                    320,
                    8509,
                    10256,
                    220,
                    19,
                    7861,
                    320,
                    8509,
                    10256,
                    220,
                    19,
                    8,
                    320,
                    56029,
                    438,
                    320,
                    56029,
                    1962,
                    259,
                    8,
                    674,
                    87,
                    23,
                    595,
                    128009
                ],
                "raw_logprob": -18.867464065551758,
                "cons_logprob": -6.818319320678711
            },
            "proposal": {
                "tokens": [
                    "(define",
                    "-f",
                    "un",
                    " inv",
                    " ((",
                    "s",
                    " (",
                    "Bit",
                    "Vec",
                    " ",
                    "4",
                    "))",
                    " (",
                    "t",
                    " (",
                    "Bit",
                    "Vec",
                    " ",
                    "4",
                    ")))",
                    " (",
                    "Bit",
                    "Vec",
                    " ",
                    "4",
                    ")",
                    " #",
                    "x",
                    "0",
                    ")",
                    "<|eot_id|>"
                ],
                "token_ids": [
                    69647,
                    2269,
                    359,
                    1558,
                    1819,
                    82,
                    320,
                    8509,
                    10256,
                    220,
                    19,
                    595,
                    320,
                    83,
                    320,
                    8509,
                    10256,
                    220,
                    19,
                    7861,
                    320,
                    8509,
                    10256,
                    220,
                    19,
                    8,
                    674,
                    87,
                    15,
                    8,
                    128009
                ],
                "raw_logprob": -13.268617630004883,
                "cons_logprob": -1.860690712928772
            },
            "acceptance_prob": 1,
            "accepted": true
        },
        {
            "current": {
                "tokens": [
                    "(define",
                    "-f",
                    "un",
                    " inv",
                    " ((",
                    "s",
                    " (",
                    "Bit",
                    "Vec",
                    " ",
                    "4",
                    "))",
                    " (",
                    "t",
                    " (",
                    "Bit",
                    "Vec",
                    " ",
                    "4",
                    ")))",
                    " (",
                    "Bit",
                    "Vec",
                    " ",
                    "4",
                    ")",
                    " #",
                    "x",
                    "0",
                    ")",
                    "<|eot_id|>"
                ],
                "token_ids": [
                    69647,
                    2269,
                    359,
                    1558,
                    1819,
                    82,
                    320,
                    8509,
                    10256,
                    220,
                    19,
                    595,
                    320,
                    83,
                    320,
                    8509,
                    10256,
                    220,
                    19,
                    7861,
                    320,
                    8509,
                    10256,
                    220,
                    19,
                    8,
                    674,
                    87,
                    15,
                    8,
                    128009
                ],
                "raw_logprob": -13.268617630004883,
                "cons_logprob": -1.860690712928772
            },
            "proposal": {
                "tokens": [
                    "(define",
                    "-f",
                    "un",
                    " inv",
                    " ((",
                    "s",
                    " (",
                    "Bit",
                    "Vec",
                    " ",
                    "4",
                    "))",
                    " (",
                    "t",
                    " (",
                    "Bit",
                    "Vec",
                    " ",
                    "4",
                    ")))",
                    " (",
                    "Bit",
                    "Vec",
                    " ",
                    "4",
                    ")",
                    " #",
                    "x",
                    "0",
                    ")",
                    "<|eot_id|>"
                ],
                "token_ids": [
                    69647,
                    2269,
                    359,
                    1558,
                    1819,
                    82,
                    320,
                    8509,
                    10256,
                    220,
                    19,
                    595,
                    320,
                    83,
                    320,
                    8509,
                    10256,
                    220,
                    19,
                    7861,
                    320,
                    8509,
                    10256,
                    220,
                    19,
                    8,
                    674,
                    87,
                    15,
                    8,
                    128009
                ],
                "raw_logprob": -13.268617630004883,
                "cons_logprob": -1.860690712928772
            },
            "acceptance_prob": 1,
            "accepted": true
        },
        {
            "current": {
                "tokens": [
                    "(define",
                    "-f",
                    "un",
                    " inv",
                    " ((",
                    "s",
                    " (",
                    "Bit",
                    "Vec",
                    " ",
                    "4",
                    "))",
                    " (",
                    "t",
                    " (",
                    "Bit",
                    "Vec",
                    " ",
                    "4",
                    ")))",
                    " (",
                    "Bit",
                    "Vec",
                    " ",
                    "4",
                    ")",
                    " #",
                    "x",
                    "0",
                    ")",
                    "<|eot_id|>"
                ],
                "token_ids": [
                    69647,
                    2269,
                    359,
                    1558,
                    1819,
                    82,
                    320,
                    8509,
                    10256,
                    220,
                    19,
                    595,
                    320,
                    83,
                    320,
                    8509,
                    10256,
                    220,
                    19,
                    7861,
                    320,
                    8509,
                    10256,
                    220,
                    19,
                    8,
                    674,
                    87,
                    15,
                    8,
                    128009
                ],
                "raw_logprob": -13.268617630004883,
                "cons_logprob": -1.860690712928772
            },
            "proposal": {
                "tokens": [
                    "(define",
                    "-f",
                    "un",
                    " inv",
                    " ((",
                    "s",
                    " (",
                    "Bit",
                    "Vec",
                    " ",
                    "4",
                    "))",
                    " (",
                    "t",
                    " (",
                    "Bit",
                    "Vec",
                    " ",
                    "4",
                    ")))",
                    " (",
                    "Bit",
                    "Vec",
                    " ",
                    "4",
                    ")",
                    " #",
                    "x",
                    "7",
                    ")",
                    "<|eot_id|>"
                ],
                "token_ids": [
                    69647,
                    2269,
                    359,
                    1558,
                    1819,
                    82,
                    320,
                    8509,
                    10256,
                    220,
                    19,
                    595,
                    320,
                    83,
                    320,
                    8509,
                    10256,
                    220,
                    19,
                    7861,
                    320,
                    8509,
                    10256,
                    220,
                    19,
                    8,
                    674,
                    87,
                    22,
                    8,
                    128009
                ],
                "raw_logprob": -12.90035629272461,
                "cons_logprob": -2.2356908321380615
            },
            "acceptance_prob": 1,
            "accepted": true
        },
        {
            "current": {
                "tokens": [
                    "(define",
                    "-f",
                    "un",
                    " inv",
                    " ((",
                    "s",
                    " (",
                    "Bit",
                    "Vec",
                    " ",
                    "4",
                    "))",
                    " (",
                    "t",
                    " (",
                    "Bit",
                    "Vec",
                    " ",
                    "4",
                    ")))",
                    " (",
                    "Bit",
                    "Vec",
                    " ",
                    "4",
                    ")",
                    " #",
                    "x",
                    "7",
                    ")",
                    "<|eot_id|>"
                ],
                "token_ids": [
                    69647,
                    2269,
                    359,
                    1558,
                    1819,
                    82,
                    320,
                    8509,
                    10256,
                    220,
                    19,
                    595,
                    320,
                    83,
                    320,
                    8509,
                    10256,
                    220,
                    19,
                    7861,
                    320,
                    8509,
                    10256,
                    220,
                    19,
                    8,
                    674,
                    87,
                    22,
                    8,
                    128009
                ],
                "raw_logprob": -12.90035629272461,
                "cons_logprob": -2.2356908321380615
            },
            "proposal": {
                "tokens": [
                    "(define",
                    "-f",
                    "un",
                    " inv",
                    " ((",
                    "s",
                    " (",
                    "Bit",
                    "Vec",
                    " ",
                    "4",
                    "))",
                    " (",
                    "t",
                    " (",
                    "Bit",
                    "Vec",
                    " ",
                    "4",
                    ")))",
                    " (",
                    "Bit",
                    "Vec",
                    " ",
                    "4",
                    ")",
                    " #",
                    "x",
                    "8",
                    ")",
                    "<|eot_id|>"
                ],
                "token_ids": [
                    69647,
                    2269,
                    359,
                    1558,
                    1819,
                    82,
                    320,
                    8509,
                    10256,
                    220,
                    19,
                    595,
                    320,
                    83,
                    320,
                    8509,
                    10256,
                    220,
                    19,
                    7861,
                    320,
                    8509,
                    10256,
                    220,
                    19,
                    8,
                    674,
                    87,
                    23,
                    8,
                    128009
                ],
                "raw_logprob": -12.42046070098877,
                "cons_logprob": -1.860690712928772
            },
            "acceptance_prob": 1,
            "accepted": true
        },
        {
            "current": {
                "tokens": [
                    "(define",
                    "-f",
                    "un",
                    " inv",
                    " ((",
                    "s",
                    " (",
                    "Bit",
                    "Vec",
                    " ",
                    "4",
                    "))",
                    " (",
                    "t",
                    " (",
                    "Bit",
                    "Vec",
                    " ",
                    "4",
                    ")))",
                    " (",
                    "Bit",
                    "Vec",
                    " ",
                    "4",
                    ")",
                    " #",
                    "x",
                    "8",
                    ")",
                    "<|eot_id|>"
                ],
                "token_ids": [
                    69647,
                    2269,
                    359,
                    1558,
                    1819,
                    82,
                    320,
                    8509,
                    10256,
                    220,
                    19,
                    595,
                    320,
                    83,
                    320,
                    8509,
                    10256,
                    220,
                    19,
                    7861,
                    320,
                    8509,
                    10256,
                    220,
                    19,
                    8,
                    674,
                    87,
                    23,
                    8,
                    128009
                ],
                "raw_logprob": -12.42046070098877,
                "cons_logprob": -1.860690712928772
            },
            "proposal": {
                "tokens": [
                    "(def",
                    "ine",
                    "-f",
                    "un",
                    " inv",
                    " ((",
                    "s",
                    " (",
                    "Bit",
                    "Vec",
                    " ",
                    "4",
                    "))",
                    " (",
                    "t",
                    " (",
                    "Bit",
                    "Vec",
                    " ",
                    "4",
                    ")))",
                    " (",
                    "Bit",
                    "Vec",
                    " ",
                    "4",
                    ")",
                    " (",
                    "b",
                    "vn",
                    "eg",
                    " (",
                    "b",
                    "vn",
                    "eg",
                    " t",
                    ")))",
                    "<|eot_id|>"
                ],
                "token_ids": [
                    21941,
                    483,
                    2269,
                    359,
                    1558,
                    1819,
                    82,
                    320,
                    8509,
                    10256,
                    220,
                    19,
                    595,
                    320,
                    83,
                    320,
                    8509,
                    10256,
                    220,
                    19,
                    7861,
                    320,
                    8509,
                    10256,
                    220,
                    19,
                    8,
                    320,
                    65,
                    29238,
                    797,
                    320,
                    65,
                    29238,
                    797,
                    259,
                    7861,
                    128009
                ],
                "raw_logprob": -23.25323486328125,
                "cons_logprob": -8.863286972045898
            },
            "acceptance_prob": 0.021705753763821608,
            "accepted": false
        },
        {
            "current": {
                "tokens": [
                    "(define",
                    "-f",
                    "un",
                    " inv",
                    " ((",
                    "s",
                    " (",
                    "Bit",
                    "Vec",
                    " ",
                    "4",
                    "))",
                    " (",
                    "t",
                    " (",
                    "Bit",
                    "Vec",
                    " ",
                    "4",
                    ")))",
                    " (",
                    "Bit",
                    "Vec",
                    " ",
                    "4",
                    ")",
                    " #",
                    "x",
                    "8",
                    ")",
                    "<|eot_id|>"
                ],
                "token_ids": [
                    69647,
                    2269,
                    359,
                    1558,
                    1819,
                    82,
                    320,
                    8509,
                    10256,
                    220,
                    19,
                    595,
                    320,
                    83,
                    320,
                    8509,
                    10256,
                    220,
                    19,
                    7861,
                    320,
                    8509,
                    10256,
                    220,
                    19,
                    8,
                    674,
                    87,
                    23,
                    8,
                    128009
                ],
                "raw_logprob": -12.42046070098877,
                "cons_logprob": -1.860690712928772
            },
            "proposal": {
                "tokens": [
                    "(define",
                    "-f",
                    "un",
                    " inv",
                    " ((",
                    "s",
                    " (",
                    "Bit",
                    "Vec",
                    " ",
                    "4",
                    "))",
                    " (",
                    "t",
                    " (",
                    "Bit",
                    "Vec",
                    " ",
                    "4",
                    ")))",
                    " (",
                    "Bit",
                    "Vec",
                    " ",
                    "4",
                    ")",
                    " #",
                    "x",
                    "8",
                    ")",
                    "<|eot_id|>"
                ],
                "token_ids": [
                    69647,
                    2269,
                    359,
                    1558,
                    1819,
                    82,
                    320,
                    8509,
                    10256,
                    220,
                    19,
                    595,
                    320,
                    83,
                    320,
                    8509,
                    10256,
                    220,
                    19,
                    7861,
                    320,
                    8509,
                    10256,
                    220,
                    19,
                    8,
                    674,
                    87,
                    23,
                    8,
                    128009
                ],
                "raw_logprob": -12.42046070098877,
                "cons_logprob": -1.860690712928772
            },
            "acceptance_prob": 1,
            "accepted": true
        },
        {
            "current": {
                "tokens": [
                    "(define",
                    "-f",
                    "un",
                    " inv",
                    " ((",
                    "s",
                    " (",
                    "Bit",
                    "Vec",
                    " ",
                    "4",
                    "))",
                    " (",
                    "t",
                    " (",
                    "Bit",
                    "Vec",
                    " ",
                    "4",
                    ")))",
                    " (",
                    "Bit",
                    "Vec",
                    " ",
                    "4",
                    ")",
                    " #",
                    "x",
                    "8",
                    ")",
                    "<|eot_id|>"
                ],
                "token_ids": [
                    69647,
                    2269,
                    359,
                    1558,
                    1819,
                    82,
                    320,
                    8509,
                    10256,
                    220,
                    19,
                    595,
                    320,
                    83,
                    320,
                    8509,
                    10256,
                    220,
                    19,
                    7861,
                    320,
                    8509,
                    10256,
                    220,
                    19,
                    8,
                    674,
                    87,
                    23,
                    8,
                    128009
                ],
                "raw_logprob": -12.42046070098877,
                "cons_logprob": -1.860690712928772
            },
            "proposal": {
                "tokens": [
                    "(define",
                    "-f",
                    "un",
                    " inv",
                    " ((",
                    "s",
                    " (",
                    "Bit",
                    "Vec",
                    " ",
                    "4",
                    "))",
                    " (",
                    "t",
                    " (",
                    "Bit",
                    "Vec",
                    " ",
                    "4",
                    ")))",
                    " (",
                    "Bit",
                    "Vec",
                    " ",
                    "4",
                    ")",
                    " (",
                    "b",
                    "vn",
                    "eg",
                    " #",
                    "x",
                    "8",
                    "))",
                    "<|eot_id|>"
                ],
                "token_ids": [
                    69647,
                    2269,
                    359,
                    1558,
                    1819,
                    82,
                    320,
                    8509,
                    10256,
                    220,
                    19,
                    595,
                    320,
                    83,
                    320,
                    8509,
                    10256,
                    220,
                    19,
                    7861,
                    320,
                    8509,
                    10256,
                    220,
                    19,
                    8,
                    320,
                    65,
                    29238,
                    797,
                    674,
                    87,
                    23,
                    595,
                    128009
                ],
                "raw_logprob": -14.940363883972168,
                "cons_logprob": -3.3835368156433105
            },
            "acceptance_prob": 0.3689636754622646,
            "accepted": false
        },
        {
            "current": {
                "tokens": [
                    "(define",
                    "-f",
                    "un",
                    " inv",
                    " ((",
                    "s",
                    " (",
                    "Bit",
                    "Vec",
                    " ",
                    "4",
                    "))",
                    " (",
                    "t",
                    " (",
                    "Bit",
                    "Vec",
                    " ",
                    "4",
                    ")))",
                    " (",
                    "Bit",
                    "Vec",
                    " ",
                    "4",
                    ")",
                    " #",
                    "x",
                    "8",
                    ")",
                    "<|eot_id|>"
                ],
                "token_ids": [
                    69647,
                    2269,
                    359,
                    1558,
                    1819,
                    82,
                    320,
                    8509,
                    10256,
                    220,
                    19,
                    595,
                    320,
                    83,
                    320,
                    8509,
                    10256,
                    220,
                    19,
                    7861,
                    320,
                    8509,
                    10256,
                    220,
                    19,
                    8,
                    674,
                    87,
                    23,
                    8,
                    128009
                ],
                "raw_logprob": -12.42046070098877,
                "cons_logprob": -1.860690712928772
            },
            "proposal": {
                "tokens": [
                    "(define",
                    "-f",
                    "un",
                    " inv",
                    " ((",
                    "s",
                    " (",
                    "Bit",
                    "Vec",
                    " ",
                    "4",
                    "))",
                    " (",
                    "t",
                    " (",
                    "Bit",
                    "Vec",
                    " ",
                    "4",
                    ")))",
                    " (",
                    "Bit",
                    "Vec",
                    " ",
                    "4",
                    ")",
                    " (",
                    "b",
                    "vn",
                    "eg",
                    " (",
                    "b",
                    "vn",
                    "eg",
                    " t",
                    ")))",
                    "<|eot_id|>"
                ],
                "token_ids": [
                    69647,
                    2269,
                    359,
                    1558,
                    1819,
                    82,
                    320,
                    8509,
                    10256,
                    220,
                    19,
                    595,
                    320,
                    83,
                    320,
                    8509,
                    10256,
                    220,
                    19,
                    7861,
                    320,
                    8509,
                    10256,
                    220,
                    19,
                    8,
                    320,
                    65,
                    29238,
                    797,
                    320,
                    65,
                    29238,
                    797,
                    259,
                    7861,
                    128009
                ],
                "raw_logprob": -14.252828598022461,
                "cons_logprob": -4.891660690307617
            },
            "acceptance_prob": 1,
            "accepted": true
        },
        {
            "current": {
                "tokens": [
                    "(define",
                    "-f",
                    "un",
                    " inv",
                    " ((",
                    "s",
                    " (",
                    "Bit",
                    "Vec",
                    " ",
                    "4",
                    "))",
                    " (",
                    "t",
                    " (",
                    "Bit",
                    "Vec",
                    " ",
                    "4",
                    ")))",
                    " (",
                    "Bit",
                    "Vec",
                    " ",
                    "4",
                    ")",
                    " (",
                    "b",
                    "vn",
                    "eg",
                    " (",
                    "b",
                    "vn",
                    "eg",
                    " t",
                    ")))",
                    "<|eot_id|>"
                ],
                "token_ids": [
                    69647,
                    2269,
                    359,
                    1558,
                    1819,
                    82,
                    320,
                    8509,
                    10256,
                    220,
                    19,
                    595,
                    320,
                    83,
                    320,
                    8509,
                    10256,
                    220,
                    19,
                    7861,
                    320,
                    8509,
                    10256,
                    220,
                    19,
                    8,
                    320,
                    65,
                    29238,
                    797,
                    320,
                    65,
                    29238,
                    797,
                    259,
                    7861,
                    128009
                ],
                "raw_logprob": -14.252828598022461,
                "cons_logprob": -4.891660690307617
            },
            "proposal": {
                "tokens": [
                    "(define",
                    "-f",
                    "un",
                    " inv",
                    " ((",
                    "s",
                    " (",
                    "Bit",
                    "Vec",
                    " ",
                    "4",
                    "))",
                    " (",
                    "t",
                    " (",
                    "Bit",
                    "Vec",
                    " ",
                    "4",
                    ")))",
                    " (",
                    "Bit",
                    "Vec",
                    " ",
                    "4",
                    ")",
                    " (",
                    "b",
                    "vn",
                    "eg",
                    " #",
                    "x",
                    "0",
                    "))",
                    "<|eot_id|>"
                ],
                "token_ids": [
                    69647,
                    2269,
                    359,
                    1558,
                    1819,
                    82,
                    320,
                    8509,
                    10256,
                    220,
                    19,
                    595,
                    320,
                    83,
                    320,
                    8509,
                    10256,
                    220,
                    19,
                    7861,
                    320,
                    8509,
                    10256,
                    220,
                    19,
                    8,
                    320,
                    65,
                    29238,
                    797,
                    674,
                    87,
                    15,
                    595,
                    128009
                ],
                "raw_logprob": -17.161420822143555,
                "cons_logprob": -4.884097099304199
            },
            "acceptance_prob": 0.054141417385966666,
            "accepted": false
        },
        {
            "current": {
                "tokens": [
                    "(define",
                    "-f",
                    "un",
                    " inv",
                    " ((",
                    "s",
                    " (",
                    "Bit",
                    "Vec",
                    " ",
                    "4",
                    "))",
                    " (",
                    "t",
                    " (",
                    "Bit",
                    "Vec",
                    " ",
                    "4",
                    ")))",
                    " (",
                    "Bit",
                    "Vec",
                    " ",
                    "4",
                    ")",
                    " (",
                    "b",
                    "vn",
                    "eg",
                    " (",
                    "b",
                    "vn",
                    "eg",
                    " t",
                    ")))",
                    "<|eot_id|>"
                ],
                "token_ids": [
                    69647,
                    2269,
                    359,
                    1558,
                    1819,
                    82,
                    320,
                    8509,
                    10256,
                    220,
                    19,
                    595,
                    320,
                    83,
                    320,
                    8509,
                    10256,
                    220,
                    19,
                    7861,
                    320,
                    8509,
                    10256,
                    220,
                    19,
                    8,
                    320,
                    65,
                    29238,
                    797,
                    320,
                    65,
                    29238,
                    797,
                    259,
                    7861,
                    128009
                ],
                "raw_logprob": -14.252828598022461,
                "cons_logprob": -4.891660690307617
            },
            "proposal": {
                "tokens": [
                    "(define",
                    "-f",
                    "un",
                    " inv",
                    " ((",
                    "s",
                    " (",
                    "Bit",
                    "Vec",
                    " ",
                    "4",
                    "))",
                    " (",
                    "t",
                    " (",
                    "Bit",
                    "Vec",
                    " ",
                    "4",
                    ")))",
                    " (",
                    "Bit",
                    "Vec",
                    " ",
                    "4",
                    ")",
                    " (",
                    "bv",
                    "not",
                    " t",
                    "))",
                    "<|eot_id|>"
                ],
                "token_ids": [
                    69647,
                    2269,
                    359,
                    1558,
                    1819,
                    82,
                    320,
                    8509,
                    10256,
                    220,
                    19,
                    595,
                    320,
                    83,
                    320,
                    8509,
                    10256,
                    220,
                    19,
                    7861,
                    320,
                    8509,
                    10256,
                    220,
                    19,
                    8,
                    320,
                    56029,
                    1962,
                    259,
                    595,
                    128009
                ],
                "raw_logprob": -12.709700584411621,
                "cons_logprob": -3.126034736633301
            },
            "acceptance_prob": 0.8005166557620271,
            "accepted": true
        },
        {
            "current": {
                "tokens": [
                    "(define",
                    "-f",
                    "un",
                    " inv",
                    " ((",
                    "s",
                    " (",
                    "Bit",
                    "Vec",
                    " ",
                    "4",
                    "))",
                    " (",
                    "t",
                    " (",
                    "Bit",
                    "Vec",
                    " ",
                    "4",
                    ")))",
                    " (",
                    "Bit",
                    "Vec",
                    " ",
                    "4",
                    ")",
                    " (",
                    "bv",
                    "not",
                    " t",
                    "))",
                    "<|eot_id|>"
                ],
                "token_ids": [
                    69647,
                    2269,
                    359,
                    1558,
                    1819,
                    82,
                    320,
                    8509,
                    10256,
                    220,
                    19,
                    595,
                    320,
                    83,
                    320,
                    8509,
                    10256,
                    220,
                    19,
                    7861,
                    320,
                    8509,
                    10256,
                    220,
                    19,
                    8,
                    320,
                    56029,
                    1962,
                    259,
                    595,
                    128009
                ],
                "raw_logprob": -12.709700584411621,
                "cons_logprob": -3.126034736633301
            },
            "proposal": {
                "tokens": [
                    "(define",
                    "-f",
                    "un",
                    " inv",
                    " ((",
                    "s",
                    " (",
                    "Bit",
                    "Vec",
                    " ",
                    "4",
                    "))",
                    " (",
                    "t",
                    " (",
                    "Bit",
                    "Vec",
                    " ",
                    "4",
                    ")))",
                    " (",
                    "Bit",
                    "Vec",
                    " ",
                    "4",
                    ")",
                    " #",
                    "x",
                    "7",
                    ")",
                    "<|eot_id|>"
                ],
                "token_ids": [
                    69647,
                    2269,
                    359,
                    1558,
                    1819,
                    82,
                    320,
                    8509,
                    10256,
                    220,
                    19,
                    595,
                    320,
                    83,
                    320,
                    8509,
                    10256,
                    220,
                    19,
                    7861,
                    320,
                    8509,
                    10256,
                    220,
                    19,
                    8,
                    674,
                    87,
                    22,
                    8,
                    128009
                ],
                "raw_logprob": -12.90035629272461,
                "cons_logprob": -2.2356908321380615
            },
            "acceptance_prob": 0.33925623121766796,
            "accepted": true
        }
    ]
}